permuta/__init__.py
permuta/cli.py
permuta/py.typed
permuta/bisc/__init__.py
permuta/bisc/bisc.py
permuta/bisc/bisc_subfunctions.py
permuta/bisc/perm_properties.py
permuta/enumeration_strategies/__init__.py
permuta/enumeration_strategies/abstract_strategy.py
permuta/enumeration_strategies/core_strategies.py
permuta/enumeration_strategies/finitely_many_simples.py
permuta/enumeration_strategies/insertion_encodable.py
permuta/misc/__init__.py
permuta/misc/display.py
permuta/misc/math.py
permuta/misc/union_find.py
permuta/patterns/__init__.py
permuta/patterns/bivincularpatt.py
permuta/patterns/meshpatt.py
permuta/patterns/patt.py
permuta/patterns/perm.py
permuta/perm_sets/__init__.py
permuta/perm_sets/basis.py
permuta/perm_sets/permset.py
permuta/permutils/__init__.py
permuta/permutils/bijections.py
permuta/permutils/finite.py
permuta/permutils/groups.py
permuta/permutils/insertion_encodable.py
permuta/permutils/pin_words.py
permuta/permutils/pinword_util.py
permuta/permutils/polynomial.py
permuta/permutils/statistics.py
permuta/permutils/symmetry.py
permuta/resources/bisc/Baxter_bad_len8.json
permuta/resources/bisc/Baxter_good_len8.json
permuta/resources/bisc/SimSun_bad_len8.json
permuta/resources/bisc/SimSun_bad_len9.json
permuta/resources/bisc/SimSun_good_len8.json
permuta/resources/bisc/SimSun_good_len9.json
permuta/resources/bisc/West_2_stack_sortable_bad_len8.json
permuta/resources/bisc/West_2_stack_sortable_good_len8.json
permuta/resources/bisc/av_231_and_mesh_bad_len8.json
permuta/resources/bisc/av_231_and_mesh_bad_len9.json
permuta/resources/bisc/av_231_and_mesh_good_len8.json
permuta/resources/bisc/av_231_and_mesh_good_len9.json
permuta/resources/bisc/dihedral_bad_len8.json
permuta/resources/bisc/dihedral_good_len8.json
permuta/resources/bisc/forest_like_bad_len8.json
permuta/resources/bisc/forest_like_good_len8.json
permuta/resources/bisc/in_alternating_group_bad_len8.json
permuta/resources/bisc/in_alternating_group_good_len8.json
permuta-2.3.1.dist-info/METADATA
permuta-2.3.1.dist-info/WHEEL
permuta-2.3.1.dist-info/entry_points.txt
permuta-2.3.1.dist-info/licenses/LICENSE
permuta-2.3.1.dist-info/RECORD
