Metadata-Version: 2.4
Name: permuta
Version: 2.3.1
Summary: A comprehensive high performance permutation library.
Project-URL: Source, https://github.com/PermutaTriangle/Permuta
Project-URL: Tracker, https://github.com/PermutaTriangle/Permuta/issues
Author-email: Permuta Triangle <permutatriangle@gmail.com>
License: BSD-3-Clause
License-File: LICENSE
Keywords: avoid,contain,mesh,occurrence,patt,pattern,perm,permutation,statistic
Classifier: Development Status :: 5 - Production/Stable
Classifier: Intended Audience :: Education
Classifier: Intended Audience :: Science/Research
Classifier: License :: OSI Approved :: BSD License
Classifier: Programming Language :: Python :: 3.10
Classifier: Programming Language :: Python :: 3.11
Classifier: Programming Language :: Python :: 3.12
Classifier: Programming Language :: Python :: 3.13
Classifier: Programming Language :: Python :: Implementation :: CPython
Classifier: Programming Language :: Python :: Implementation :: PyPy
Classifier: Topic :: Education
Classifier: Topic :: Scientific/Engineering :: Mathematics
Requires-Python: >=3.10
Requires-Dist: automata-lib==9.0.0
